protos_finance/__init__.py
protos_finance/common/__init__.py
protos_finance/common/cache_utils.py
protos_finance/common/common_utils.py
protos_finance/common/exceptions.py
protos_finance/common/helper/__init__.py
protos_finance/common/helper/context.py
protos_finance/common/helper/example_plugin.py
protos_finance/common/helper/field.py
protos_finance/common/helper/file_processfile.py
protos_finance/common/helper/grpc_wrapper.py
protos_finance/common/helper/log_filter.py
protos_finance/common/interceptor/__init__.py
protos_finance/common/interceptor/client_interceptor/__init__.py
protos_finance/common/interceptor/client_interceptor/base.py
protos_finance/common/interceptor/client_interceptor/customer_top.py
protos_finance/common/interceptor/server_interceptor/__init__.py
protos_finance/common/interceptor/server_interceptor/base.py
protos_finance/common/interceptor/server_interceptor/customer_top.py
protos_finance/finance/__init__.py
protos_finance/finance/reqData_pb2.py
protos_finance/finance/reqData_pb2_grpc.py
protos_finance/generaterUtil.py
protos_finance/health.proto
protos_finance/reqData.proto
protos_finance/user/__init__.py
protos_finance/user/user.proto
protos_finance/user/user_pb2.py
protos_finance/user/user_pb2_grpc.py
protos_finance-0.1.0.dist-info/METADATA
protos_finance-0.1.0.dist-info/WHEEL
protos_finance-0.1.0.dist-info/RECORD
