Metadata-Version: 2.1
Name: protos_finance
Version: 0.1.0
Summary: 
License: MIT
Author: 41aasdqweq
Author-email: tk230@163.com
Requires-Python: >=3.12,<4.0
Classifier: License :: OSI Approved :: MIT License
Classifier: Programming Language :: Python :: 3
Classifier: Programming Language :: Python :: 3.12
Requires-Dist: grpcio (>=1.43.0,<2.0.0)
Requires-Dist: grpcio-tools (>=1.43.0,<2.0.0)
Requires-Dist: pypinyin (>=0.51.0,<0.52.0)
